aliyun_python_sdk_iot_client-0.0.14.dist-info/LICENSE.txt
aliyun_python_sdk_iot_client-0.0.14.dist-info/METADATA
aliyun_python_sdk_iot_client-0.0.14.dist-info/RECORD
aliyun_python_sdk_iot_client-0.0.14.dist-info/WHEEL
aliyun_python_sdk_iot_client-0.0.14.dist-info/top_level.txt
aliyunsdkiotclient/AliyunIotMqttClient.py
aliyunsdkiotclient/__init__.py
aliyunsdkiotclient/__version__.py
aliyunsdkiotclient/api.py
aliyunsdkiotclient/exceptions.py
aliyunsdkiotclient/status_codes.py
aliyunsdkiotclient/structures.py
test/__init__.py
