Metadata-Version: 2.1
Name: aliyun-python-sdk-iot-client
Version: 0.0.14
Summary: aliyun iot client sdk
Home-page: http://develop.aliyun.com/sdk/python
Author: Aliyun
Author-email: aliyun-developers-efficiency@list.alibaba-inc.com
License: Apache 2.0
Platform: UNKNOWN
Classifier: Intended Audience :: Developers
Classifier: Natural Language :: English
Classifier: License :: OSI Approved :: Apache Software License
Classifier: Programming Language :: Python
Classifier: Programming Language :: Python :: 2
Classifier: Programming Language :: Python :: 2.6
Classifier: Programming Language :: Python :: 2.7
Classifier: Programming Language :: Python :: 3
Classifier: Programming Language :: Python :: 3.4
Classifier: Programming Language :: Python :: 3.5
Classifier: Programming Language :: Python :: 3.6
Classifier: Programming Language :: Python :: Implementation :: CPython
Classifier: Programming Language :: Python :: Implementation :: PyPy
Requires-Python: >=2.6, !=3.0.*, !=3.1.*, !=3.2.*, !=3.3.*
Requires-Dist: certifi (>=2018.1.18)
Requires-Dist: paho-mqtt (>=1.3.1)
Requires-Dist: pycrypto (>=2.6.1)
